icotest_voice/__init__.py
icotest_voice/api_client.py
icotest_voice/api_response.py
icotest_voice/configuration.py
icotest_voice/exceptions.py
icotest_voice/py.typed
icotest_voice/rest.py
icotest_voice/api/__init__.py
icotest_voice/api/controllers_api.py
icotest_voice/api/devices_api.py
icotest_voice/api/requests_api.py
icotest_voice/models/__init__.py
icotest_voice/models/controller.py
icotest_voice/models/device.py
icotest_voice/models/get_test_result_file_list200_response.py
icotest_voice/models/get_test_result_file_list200_response_files_inner.py
icotest_voice/models/host_config.py
icotest_voice/models/post_device_register_request.py
icotest_voice/models/request.py
icotest_voice-1.0.44.dist-info/LICENSE
icotest_voice-1.0.44.dist-info/METADATA
icotest_voice-1.0.44.dist-info/WHEEL
icotest_voice-1.0.44.dist-info/top_level.txt
icotest_voice-1.0.44.dist-info/RECORD
