Metadata-Version: 2.1
Name: icotest-voice
Version: 1.0.44
Summary: Icotest Voice API
Home-page: 
Author: Shaun Hirst
Author-email: Shaun Hirst <shaun.hirst@3adesign.co.uk>, Ivo Shipkaliev <ivo@3adesign.co.uk>
License: Copyright © 2024 3ADesign Limited
Keywords: OpenAPI,OpenAPI-Generator,Icotest Voice
Classifier: License :: OSI Approved :: MIT License
Classifier: Programming Language :: Python
Classifier: Programming Language :: Python :: 3
Requires-Python: >=3.7
License-File: LICENSE
Requires-Dist: typing-extensions >=4.7.1
Requires-Dist: urllib3 <2.1.0,>=1.25.3
Requires-Dist: python-dateutil >=2.8.2
Requires-Dist: pydantic >=2
Requires-Dist: setuptools >=21.0.0
